wecom_worktool/__init__.py
wecom_worktool/py.typed
wecom_worktool-0.1.0.dist-info/METADATA
wecom_worktool-0.1.0.dist-info/WHEEL
wecom_worktool-0.1.0.dist-info/RECORD
