Metadata-Version: 2.4
Name: wecom-worktool
Version: 0.1.0
Summary: 企业微信WorkTool机器人API的封装。
Author-email: YiZixuan <sqkkyzx@qq.com>
Requires-Python: >=3.11
Requires-Dist: requests
